kode/__init__.py
kode/triangle.py
segitiga-1.0.dist-info/LICENSE
segitiga-1.0.dist-info/METADATA
segitiga-1.0.dist-info/WHEEL
segitiga-1.0.dist-info/top_level.txt
segitiga-1.0.dist-info/RECORD
