Metadata-Version: 2.1
Name: segitiga
Version: 1.0
Summary: Menghitung segitiga
Home-page: https://github.com/SabillillahX/pipi.git
Author: SabillillahX
Author-email: <sabillillahxtkj@gmail.com>
License: MIT
Keywords: golden_ratio,golden
Classifier: Development Status :: 1 - Planning
License-File: LICENSE
